chatbot_nlu/__init__.py
chatbot_nlu/components.py
chatbot_nlu/config.py
chatbot_nlu/constants.py
chatbot_nlu/convert.py
chatbot_nlu/data_router.py
chatbot_nlu/evaluate.py
chatbot_nlu/model.py
chatbot_nlu/persistor.py
chatbot_nlu/project.py
chatbot_nlu/registry.py
chatbot_nlu/run.py
chatbot_nlu/server.py
chatbot_nlu/train.py
chatbot_nlu/version.py
chatbot_nlu/classifiers/__init__.py
chatbot_nlu/classifiers/embedding_bert_intent_classifier.py
chatbot_nlu/classifiers/embedding_bert_intent_estimator_classifier.py
chatbot_nlu/classifiers/embedding_bert_sentiment_classifier.py
chatbot_nlu/classifiers/embedding_intent_classifier.py
chatbot_nlu/classifiers/entity_edit_intent.py
chatbot_nlu/classifiers/keyword_intent_classifier.py
chatbot_nlu/classifiers/mitie_intent_classifier.py
chatbot_nlu/classifiers/sklearn_intent_classifier.py
chatbot_nlu/emulators/__init__.py
chatbot_nlu/emulators/dialogflow.py
chatbot_nlu/emulators/luis.py
chatbot_nlu/emulators/wit.py
chatbot_nlu/extractors/__init__.py
chatbot_nlu/extractors/bert_bilstm_crf_entity_extractor.py
chatbot_nlu/extractors/bilstm_crf_entity_extractor.py
chatbot_nlu/extractors/crf_entity_extractor.py
chatbot_nlu/extractors/duckling_extractor.py
chatbot_nlu/extractors/duckling_http_extractor.py
chatbot_nlu/extractors/entity_synonyms.py
chatbot_nlu/extractors/jieba_pseg_extractor.py
chatbot_nlu/extractors/mitie_entity_extractor.py
chatbot_nlu/extractors/pyltp_extractor.py
chatbot_nlu/extractors/spacy_entity_extractor.py
chatbot_nlu/featurizers/__init__.py
chatbot_nlu/featurizers/bert_vectors_featurizer.py
chatbot_nlu/featurizers/count_vectors_featurizer.py
chatbot_nlu/featurizers/intent_featurizer_wordvector.py
chatbot_nlu/featurizers/mitie_featurizer.py
chatbot_nlu/featurizers/ngram_featurizer.py
chatbot_nlu/featurizers/regex_featurizer.py
chatbot_nlu/featurizers/spacy_featurizer.py
chatbot_nlu/models/__init__.py
chatbot_nlu/models/lenet.py
chatbot_nlu/models/model.py
chatbot_nlu/models/bert/__init__.py
chatbot_nlu-1.0.3.dist-info/LICENSE
chatbot_nlu-1.0.3.dist-info/METADATA
chatbot_nlu-1.0.3.dist-info/WHEEL
chatbot_nlu-1.0.3.dist-info/top_level.txt
chatbot_nlu-1.0.3.dist-info/RECORD
