Metadata-Version: 2.1
Name: chatbot-nlu
Version: 1.0.3
Summary: nlu of classifiers detection、name entity recognition、classification of chinese text
Home-page: https://github.com/charlesXu86/Chatbot_NLU
Author: xu
Author-email: charlesxu86@163.com
License: MIT
Platform: UNKNOWN
Classifier: License :: OSI Approved :: MIT License
Classifier: Programming Language :: Python :: 3.4
Classifier: Programming Language :: Python :: 3.5
Classifier: Programming Language :: Python :: 3.6
Classifier: Programming Language :: Python :: 3.7
Classifier: Programming Language :: Python :: 3.8
Classifier: Programming Language :: Python :: Implementation :: CPython
Classifier: Programming Language :: Python :: Implementation :: PyPy
Requires-Dist: bert-serving-client (==1.8.9)
Requires-Dist: bert-serving-server (==1.9.2)
